erepublik/__init__.py
erepublik/_logging.py
erepublik/_types.py
erepublik/access_points.py
erepublik/citizen.py
erepublik/classes.py
erepublik/constants.py
erepublik/utils.py
eRepublik-0.30.0.8.dist-info/AUTHORS.rst
eRepublik-0.30.0.8.dist-info/LICENSE
eRepublik-0.30.0.8.dist-info/METADATA
eRepublik-0.30.0.8.dist-info/WHEEL
eRepublik-0.30.0.8.dist-info/top_level.txt
eRepublik-0.30.0.8.dist-info/RECORD
