Metadata-Version: 2.1
Name: eRepublik
Version: 0.30.0.8
Summary: Python package for automated eRepublik playing
Home-page: https://github.com/eeriks/erepublik/
Author: Eriks Karls
Author-email: eriks@72.lv
License: GPLv3
Keywords: erepublik
Platform: UNKNOWN
Classifier: Development Status :: 4 - Beta
Classifier: Intended Audience :: Developers
Classifier: License :: OSI Approved :: GNU General Public License v3 (GPLv3)
Classifier: Natural Language :: English
Classifier: Programming Language :: Python :: 3
Classifier: Programming Language :: Python :: 3.8
Classifier: Programming Language :: Python :: 3.9
Requires-Python: >=3.8, <4
License-File: LICENSE
License-File: AUTHORS.rst
Requires-Dist: PySocks (==1.7.1)
Requires-Dist: pytz (>2021.0)
Requires-Dist: httpx (==0.22.0)
Requires-Dist: h2 (==4.1.0)
Requires-Dist: socksio (==1.0.0)
Requires-Dist: brotli (==1.0.9)
